openpyxl-stubs/__init__.pyi
openpyxl-stubs/cell/__init__.pyi
openpyxl-stubs/cell/_writer.pyi
openpyxl-stubs/cell/cell.pyi
openpyxl-stubs/cell/text.pyi
openpyxl-stubs/chart/__init__.pyi
openpyxl-stubs/chart/axis.pyi
openpyxl-stubs/reader/__init__.pyi
openpyxl-stubs/reader/drawings.pyi
openpyxl-stubs/reader/excel.pyi
openpyxl-stubs/reader/strings.pyi
openpyxl-stubs/reader/workbook.pyi
openpyxl-stubs/styles/__init__.pyi
openpyxl-stubs/styles/alignment.pyi
openpyxl-stubs/styles/borders.pyi
openpyxl-stubs/styles/colors.pyi
openpyxl-stubs/styles/differential.pyi
openpyxl-stubs/styles/fills.pyi
openpyxl-stubs/styles/fonts.pyi
openpyxl-stubs/styles/named_styles.pyi
openpyxl-stubs/styles/numbers.pyi
openpyxl-stubs/styles/protection.pyi
openpyxl-stubs/styles/styleable.pyi
openpyxl-stubs/utils/__init__.pyi
openpyxl-stubs/utils/cell.pyi
openpyxl-stubs/utils/escape.pyi
openpyxl-stubs/utils/formulas.pyi
openpyxl-stubs/workbook/__init__.pyi
openpyxl-stubs/workbook/child.pyi
openpyxl-stubs/workbook/defined_name.pyi
openpyxl-stubs/workbook/workbook.pyi
openpyxl-stubs/worksheet/__init__.pyi
openpyxl-stubs/worksheet/_reader.pyi
openpyxl-stubs/worksheet/_writer.pyi
openpyxl-stubs/worksheet/copier.pyi
openpyxl-stubs/worksheet/worksheet.pyi
openpyxl-stubs/xml/__init__.pyi
openpyxl_stubs-0.1.25.dist-info/LICENSE
openpyxl_stubs-0.1.25.dist-info/METADATA
openpyxl_stubs-0.1.25.dist-info/WHEEL
openpyxl_stubs-0.1.25.dist-info/top_level.txt
openpyxl_stubs-0.1.25.dist-info/RECORD
