Metadata-Version: 2.1
Name: openpyxl-stubs
Version: 0.1.25
Summary: Type stubs for openpyxl
Home-page: https://github.com/MartinThoma/openpyxl-stubs
Author: Martin Thoma
Author-email: info@martin-thoma.de
Maintainer: Martin Thoma
Maintainer-email: info@martin-thoma.de
License: MIT license
Keywords: utility,mypy,stubs
Classifier: Development Status :: 3 - Alpha
Classifier: Intended Audience :: Developers
Classifier: Natural Language :: English
License-File: LICENSE
